{"Title": "Charlie and the Chocolate Factory", "Year": "2005", "Rated": "PG", "Released": "15 Jul 2005", "Runtime": "115 min", "Genre": "Adventure, Comedy, Family", "Director": "Tim Burton", "Writer": "Roald Dahl, John August", "Actors": "Johnny Depp, Freddie Highmore, David Kelly", "Plot": "A young boy wins a tour through the most magnificent chocolate factory in the world, led by the world's most unusual candy maker.", "Language": "English", "Country": "United States, United Kingdom", "Awards": "Nominated for 1 Oscar. 15 wins & 52 nominations total", "Poster": "https://m.media-amazon.com/images/M/MV5BNjcxMjg1Njg2NF5BMl5BanBnXkFtZTcwMjQ4NzMzMw@@._V1_SX300.jpg", "Ratings": [{"Source": "Internet Movie Database", "Value": "6.7/10"}, {"Source": "Rotten Tomatoes", "Value": "83%"}, {"Source": "Metacritic", "Value": "72/100"}], "Metascore": "72", "imdbRating": "6.7", "imdbVotes": "490,209", "imdbID": "tt0367594", "Type": "movie", "DVD": "08 Nov 2005", "BoxOffice": "$206,459,076", "Production": "N/A", "Website": "N/A", "Response": "True"}